README.md
setup.py
ssm_search/__init__.py
ssm_search/__main__.py
ssm_search/ssm_search.py
ssm_search/version.py
ssm_search.egg-info/PKG-INFO
ssm_search.egg-info/SOURCES.txt
ssm_search.egg-info/dependency_links.txt
ssm_search.egg-info/entry_points.txt
ssm_search.egg-info/requires.txt
ssm_search.egg-info/top_level.txt