Metadata-Version: 1.1
Name: ssm-search
Version: 0.1.5
Summary: A CLI to easily search for SSM parameters
Home-page: https://github.com/dwkerwin/ssm-search
Author: Doug Kerwin
Author-email: dwkerwin@gmail.com
License: MIT
Keywords: aws-ssm,ssm parameter store
Platform: UNKNOWN
Classifier: Intended Audience :: Developers
Classifier: Natural Language :: English
Classifier: License :: OSI Approved :: MIT License
Classifier: Programming Language :: Python
Classifier: Programming Language :: Python :: 2
Classifier: Programming Language :: Python :: 2.7
Classifier: Programming Language :: Python :: 3
Classifier: Programming Language :: Python :: 3.6
